code_var/__init__.py
code_var/cli.py
code_var-0.1.3.dist-info/METADATA
code_var-0.1.3.dist-info/WHEEL
code_var-0.1.3.dist-info/entry_points.txt
code_var-0.1.3.dist-info/top_level.txt
code_var-0.1.3.dist-info/RECORD
