Metadata-Version: 2.1
Name: code-var
Version: 0.1.3
Summary: "code-var is tools for varname in cmd"
Author: JackCCC
Requires-Python: >=3.6.2,<4.0.0
Requires-Dist: bs4 (==0.0.1)
Requires-Dist: requests (==2.28.1)
Requires-Dist: typer (==0.6.1)
